bohs/__init__.py
bohs-0.1.0.dist-info/LICENSE
bohs-0.1.0.dist-info/METADATA
bohs-0.1.0.dist-info/WHEEL
bohs-0.1.0.dist-info/top_level.txt
bohs-0.1.0.dist-info/RECORD
