Metadata-Version: 2.1
Name: bohs
Version: 0.1.0
Summary: Bayesian Optimisation for Heterogeneous Spaces
Home-page: https://github.com/m-t-m/bohs
Author: Marius Tudor Morar
Author-email: author@example.com
License: UNKNOWN
Project-URL: Bug Tracker, https://github.com/m-t-m/bohs/issues
Platform: UNKNOWN
Classifier: Programming Language :: Python :: 3
Classifier: License :: OSI Approved :: MIT License
Classifier: Operating System :: OS Independent
Requires-Python: >=3.6
